{
   "type": "encounter",
   "encounter_type": "generator",
   "in_edge": "start",
   "generator_info": {
      "delay": "40h+8h",
      "spawn_edge": {
         "type": "trigger_one",
         "out_edges": [
            {
               "type": "weighted_edge",
               "out_edge": "do_nothing",
               "weight": 398
            },
            {
               "type": "weighted_edge",
               "out_edge": "spawn_koda",
               "weight": 1
            },
            {
               "type": "weighted_edge",
               "out_edge": "spawn_jacko",
               "weight": 1
            }
         ]
      }
   }
}
