{
   "type": "recipe",
   "effort": 90,
   "work_units": 5,
   "recipe_name": "i18n(nordlingmod:jobs.blacksmith.recipes.runic_mythril_comb.recipe_name)",
   "description": "i18n(nordlingmod:jobs.blacksmith.recipes.runic_mythril_comb.description)",
   "flavor": "i18n(nordlingmod:jobs.blacksmith.recipes.runic_mythril_comb.flavor)",
   "portrait": "/nordlingmod/entities/armor/runic_mythril_comb/runic_mythril_comb.png",
   "workshop": "stonehearth:blacksmith:workbench",
   "level_requirement": 6,
   "ingredients": [
      {
         "uri": "nordlingmod:mythril_ingot",
         "count": 2
      }
   ],
   "produces": [
      {
         "item": "nordlingmod:runic_mythril_comb"
      }
   ]
}