{
   "type": "recipe",
   "effort": 40,
   "work_units": 1,
   "recipe_name": "i18n(nordlingmod:jobs.herbalist.recipes.mead_recipe.recipe_name)",
   "description": "i18n(nordlingmod:jobs.herbalist.recipes.mead_recipe.description)",
   "flavor": "i18n(nordlingmod:jobs.herbalist.recipes.mead_recipe.flavor)",
   "portrait": "/nordlingmod/entities/food/mead/mead/mead.png",
   "workshop": "stonehearth:herbalist:workbench",
   "ingredients": [
      {
         "uri": "stonehearth:food:honey:honey",
         "count": 2
      }
   ],
   "produces": [
      {
         "item": "nordlingmod:food:mead:mead"
      }
   ]
}
